{
    "visual": {
        "name": "circleCard",
        "displayName": "CircleCard",
        "guid": "circleCard9284F84C9FE84659A930B54B9F68B545",
        "visualClassName": "Visual",
        "version": "1.0.0",
        "description": "",
        "supportUrl": "",
        "gitHubUrl": ""
    },
    "apiVersion": "3.8.0",
    "author": {
        "name": "",
        "email": ""
    },
    "assets": {
        "icon": "assets/icon.png"
    },
    "externalJS": [
        "node_modules/echarts/dist/echarts.js",
        "node_modules/echarts-stat/dist/ecStat.js"
    ],
    "style": "style/visual.less",
    "capabilities": "capabilities.json",
    "dependencies": null,
    "stringResources": []
}